fnss/__init__.py
fnss/release.py
fnss/units.py
fnss/util.py
fnss/adapters/__init__.py
fnss/adapters/autonetkit.py
fnss/adapters/jfed.py
fnss/adapters/mn.py
fnss/adapters/ns2.py
fnss/adapters/omnetpp.py
fnss/netconfig/__init__.py
fnss/netconfig/buffers.py
fnss/netconfig/capacities.py
fnss/netconfig/delays.py
fnss/netconfig/nodeconfig.py
fnss/netconfig/weights.py
fnss/topologies/__init__.py
fnss/topologies/datacenter.py
fnss/topologies/parsers.py
fnss/topologies/randmodels.py
fnss/topologies/simplemodels.py
fnss/topologies/topology.py
fnss/traffic/__init__.py
fnss/traffic/eventscheduling.py
fnss/traffic/trafficmatrices.py
fnss-0.8.2.data/scripts/fnss-troubleshoot
fnss-0.8.2.data/scripts/mn-fnss
fnss-0.8.2.dist-info/DESCRIPTION.rst
fnss-0.8.2.dist-info/METADATA
fnss-0.8.2.dist-info/metadata.json
fnss-0.8.2.dist-info/RECORD
fnss-0.8.2.dist-info/top_level.txt
fnss-0.8.2.dist-info/WHEEL
