Metadata-Version: 2.0
Name: fnss
Version: 0.8.2
Summary: Fast creation and configuration of topologies, traffic matrices and event schedules for network experiments
Home-page: http://fnss.github.io/
Author: Lorenzo Saino, Cosmin Cocora
Author-email: fnss.dev@gmail.com
License: BSD license
Download-URL: http://fnss.github.io/
Keywords: network,simulation,topology,traffic matrix,link capacity,delay,protocol stack
Platform: UNKNOWN
Classifier: Development Status :: 5 - Production/Stable
Classifier: Intended Audience :: Developers
Classifier: Intended Audience :: Science/Research
Classifier: Intended Audience :: Telecommunications Industry
Classifier: License :: OSI Approved :: BSD License
Classifier: Natural Language :: English
Classifier: Operating System :: OS Independent
Classifier: Programming Language :: Python :: 2
Classifier: Programming Language :: Python :: 2.7
Classifier: Programming Language :: Python :: 3
Classifier: Programming Language :: Python :: 3.4
Classifier: Programming Language :: Python :: 3.5
Classifier: Programming Language :: Python :: 3.6
Classifier: Topic :: Software Development :: Libraries :: Python Modules
Classifier: Topic :: Scientific/Engineering
Requires-Python: >=2.7.9, !=3.0.*, !=3.1.*, !=3.2.*, !=3.3.*
Requires-Dist: networkx (>=1.6)
Requires-Dist: numpy (>=1.4)
Requires-Dist: mako (>=0.4)
